traderfit_mcp_bridge/__main__.py
traderfit_mcp_bridge-0.1.1.dist-info/METADATA
traderfit_mcp_bridge-0.1.1.dist-info/WHEEL
traderfit_mcp_bridge-0.1.1.dist-info/entry_points.txt
traderfit_mcp_bridge-0.1.1.dist-info/top_level.txt
traderfit_mcp_bridge-0.1.1.dist-info/RECORD
