Metadata-Version: 2.4
Name: traderfit-mcp-bridge
Version: 0.1.1
Summary: MCP Bridge Server for TraderFitAI backend
Author-email: Kisra Fistya / TraderFitAI <kisra.fistya@gmail.com>
License: MIT License
Project-URL: Homepage, https://github.com/rizkisyaf/TraderFitAI/tree/main/traderfit-mcp-bridge
Project-URL: Repository, https://github.com/rizkisyaf/TraderFitAI/tree/main/traderfit-mcp-bridge
Classifier: Programming Language :: Python :: 3
Classifier: License :: OSI Approved :: MIT License
Classifier: Operating System :: OS Independent
Classifier: Topic :: Communications
Classifier: Intended Audience :: Developers
Requires-Python: >=3.11
Requires-Dist: modelcontextprotocol
Requires-Dist: httpx[http2]
Requires-Dist: python-dotenv
Requires-Dist: uvloop; sys_platform != "win32"
